infragpt/__init__.py
infragpt/__main__.py
infragpt/agent.py
infragpt/api_client.py
infragpt/auth.py
infragpt/bump_version.py
infragpt/config.py
infragpt/container.py
infragpt/encryption.py
infragpt/exceptions.py
infragpt/history.py
infragpt/llm_adapter.py
infragpt/main.py
infragpt/prompts.py
infragpt/shell.py
infragpt/tools.py
infragpt/images/sandbox/Dockerfile
infragpt/images/sandbox/Makefile
infragpt/llm/__init__.py
infragpt/llm/base.py
infragpt/llm/exceptions.py
infragpt/llm/models.py
infragpt/llm/router.py
infragpt/llm/providers/__init__.py
infragpt/llm/providers/anthropic_provider.py
infragpt/llm/providers/openai_provider.py
infragpt-0.1.53.dist-info/METADATA
infragpt-0.1.53.dist-info/WHEEL
infragpt-0.1.53.dist-info/entry_points.txt
infragpt-0.1.53.dist-info/RECORD
