Metadata-Version: 2.4
Name: infragpt
Version: 0.1.53
Summary: InfraGPT is an AI assistant for interactively managing your infrastructure.
Project-URL: Homepage, https://github.com/73ai/infragpt
Author-email: Priyanshu Jain <pj@73ai.org>
License: GPL-3.0-only
Classifier: License :: OSI Approved :: GNU General Public License v3 (GPLv3)
Classifier: Operating System :: OS Independent
Classifier: Programming Language :: Python :: 3
Classifier: Programming Language :: Python :: 3.13
Classifier: Topic :: System :: Systems Administration
Classifier: Topic :: Utilities
Requires-Python: >=3.13
Requires-Dist: anthropic>=0.60.0
Requires-Dist: click>=8.2.1
Requires-Dist: cryptography>=44.0.1
Requires-Dist: docker>=7.1.0
Requires-Dist: httpx>=0.28.1
Requires-Dist: openai>=1.98.0
Requires-Dist: prompt-toolkit>=3.0.51
Requires-Dist: pyperclip>=1.9.0
Requires-Dist: pyyaml>=6.0.2
Requires-Dist: rich>=14.0.0
